essence_nlp/.DS_Store
essence_nlp/__init__.py
essence_nlp/essence.cpython-311-darwin.so
essence_nlp/processing.py
essence_nlp/essence/.DS_Store
essence_nlp/essence/Cargo.lock
essence_nlp/essence/Cargo.toml
essence_nlp/essence/resources/.DS_Store
essence_nlp/essence/resources/data/frequency_dictionary_en_82_765.txt
essence_nlp/essence/resources/data/stopwords.txt
essence_nlp/essence/resources/rules/en_rules.bin
essence_nlp/essence/resources/rules/en_tokenizer.bin
essence_nlp/essence/src/lib.rs
essence_nlp-2.0.0.dist-info/LICENSE
essence_nlp-2.0.0.dist-info/METADATA
essence_nlp-2.0.0.dist-info/WHEEL
essence_nlp-2.0.0.dist-info/top_level.txt
essence_nlp-2.0.0.dist-info/RECORD
