Metadata-Version: 2.1
Name: essence-nlp
Version: 2.0.0
Summary: String processing library for advanced NLP and keyword extraction
Author-email: Jash Dubal <jsd9393@gmail.com>
Project-URL: Homepage, https://github.com/jashdubal/essence
Project-URL: Bug Tracker, https://github.com/jashdubal/essence/issues
Classifier: Programming Language :: Python :: 3
Classifier: License :: OSI Approved :: MIT License
Classifier: Operating System :: OS Independent
Requires-Python: >=3.7
License-File: LICENSE
